partitioning/__init__.py
partitioning/apps.py
partitioning/decorators.py
partitioning/utils.py
partitioning/management/commands/setup_partitioning.py
django_postgresql_partitioning-0.1.1.dist-info/LICENSE
django_postgresql_partitioning-0.1.1.dist-info/METADATA
django_postgresql_partitioning-0.1.1.dist-info/WHEEL
django_postgresql_partitioning-0.1.1.dist-info/top_level.txt
django_postgresql_partitioning-0.1.1.dist-info/RECORD
