Metadata-Version: 2.1
Name: django-postgresql-partitioning
Version: 0.1.1
Summary: Add PostgreSQL table partitioning to Django models
Home-page: https://github.com/starnavi-team/django-postgresql-partitioning
Author: starnavi.io
Author-email: hello@starnavi.io
License: BSD License
Classifier: Development Status :: 2 - Pre-Alpha
Classifier: Framework :: Django
Classifier: Environment :: Web Environment
Classifier: Intended Audience :: Developers
Classifier: License :: OSI Approved :: BSD License
Classifier: Operating System :: OS Independent
Classifier: Natural Language :: English
Classifier: Programming Language :: Python :: 3.6
Classifier: Programming Language :: Python :: 3.7
Classifier: Programming Language :: Python :: 3.8
Classifier: Programming Language :: Python :: 3.9
Classifier: Programming Language :: Python :: 3.10
Classifier: Programming Language :: Python :: 3.11
Classifier: Programming Language :: Python :: 3.12
License-File: LICENSE
Requires-Dist: Django <5.1,>=1.11
Requires-Dist: setuptools
